README.md
setup.py
linkedin_auto_comment/__init__.py
linkedin_auto_comment.egg-info/PKG-INFO
linkedin_auto_comment.egg-info/SOURCES.txt
linkedin_auto_comment.egg-info/dependency_links.txt
linkedin_auto_comment.egg-info/requires.txt
linkedin_auto_comment.egg-info/top_level.txt